lib/__init__.py
lib-4.0.0.dist-info/LICENSE
lib-4.0.0.dist-info/METADATA
lib-4.0.0.dist-info/WHEEL
lib-4.0.0.dist-info/top_level.txt
lib-4.0.0.dist-info/RECORD
